{
  "market": [
    {
      "market_id": "1",
      "market_coordinates": "BS1 5SP",
      "market_name": "Tesco"
    },
    {
      "market_id": "3",
      "market_coordinates": "BS2 8HW",
      "market_name": "M&S"
    }
  ],
  "recipe_id": "O858BCnH",
  "recipe_ingredients": "Beef(6.99/kg), Bean(3.75/kg), Red onion(0.21/each), Wild Rocket(1.67/100g)",
  "recipe_status": "canceled",
  "recipe_name": "Balsamic beef with beetroot & rocket",
  "currency": "GBP",
  "available_market": "Tesco, M&S"
}